{
  "protocolSection": {
    "identificationModule": {
      "nctId": "NCT01085526",
      "orgStudyIdInfo": {
        "id": "BasoScit"
      },
      "organization": {
        "fullName": "Aarhus University Hospital",
        "class": "OTHER"
      },
      "briefTitle": "Changes in Specific Immunoglobulin and Blood Basophil Activity During Subcutaneous Immunotherapy in Allergic Rhinitis",
      "officialTitle": "Changes in Specific Immunoglobulin and Blood Basophil Activity During Subcutaneous Immunotherapy in Patients With Allergic Rhinitis Due to Grass Pollen Allergy - a Prospective Randomized Controlled Study"
    },
    "statusModule": {
      "statusVerifiedDate": "2014-07",
      "overallStatus": "COMPLETED",
      "expandedAccessInfo": {
        "hasExpandedAccess": false
      },
      "startDateStruct": {
        "date": "2010-02"
      },
      "primaryCompletionDateStruct": {
        "date": "2014-07",
        "type": "ACTUAL"
      },
      "completionDateStruct": {
        "date": "2014-09",
        "type": "ACTUAL"
      },
      "studyFirstSubmitDate": "2010-03-10",
      "studyFirstSubmitQcDate": "2010-03-11",
      "studyFirstPostDateStruct": {
        "date": "2010-03-12",
        "type": "ESTIMATED"
      },
      "lastUpdateSubmitDate": "2015-02-16",
      "lastUpdatePostDateStruct": {
        "date": "2015-02-18",
        "type": "ESTIMATED"
      }
    },
    "sponsorCollaboratorsModule": {
      "responsibleParty": {
        "type": "PRINCIPAL_INVESTIGATOR",
        "investigatorFullName": "Pia Pedersen",
        "investigatorTitle": "MD",
        "investigatorAffiliation": "Aarhus University Hospital"
      },
      "leadSponsor": {
        "name": "Aarhus University Hospital",
        "class": "OTHER"
      },
      "collaborators": [
        {
          "name": "University of Aarhus",
          "class": "OTHER"
        },
        {
          "name": "ALK-Abelló A/S",
          "class": "INDUSTRY"
        },
        {
          "name": "Lundbeck Foundation",
          "class": "OTHER"
        }
      ]
    },
    "oversightModule": {
      "oversightHasDmc": true
    },
    "descriptionModule": {
      "briefSummary": "The trial is randomized prospective study to examine the effects of subcutaneous immunotherapy on the adaptive immune system. The trial includes 30 participants randomized to treatment or control group. The effect measures are changes in the basophil activity and biology as well as changes in plasma cells during and after treatment. Clinical outcome is assessed by QoL questionnaires and clinical testing.\n\nHypotheses:\n\n* changes in plasma cells correlate to changes in immunoglobulins and effector cell responses\n* the reduction of inflammation due to SCIT has influence on the effector cell responses\n* changes in paraclinical measurements can be related to clinical findings",
      "detailedDescription": "The investigators are recruiting 30 participants, which are randomized to receive SCIT (24) or no treatment (6) The following will be measured\n\n* the development of immunoglobulin response\n* plasma cells under updosing phase\n* changes in basophil activity under updosing and maintenance treatment\n* subtyping of allergic sensitization\n* clinical outcome and quality of life\n* changes in mast cells in the nasal mucosa\n* changes in the cell biology of the basophils"
    },
    "conditionsModule": {
      "conditions": [
        "Allergic Rhinoconjunctivitis"
      ],
      "keywords": [
        "basophil activity",
        "plasma cells",
        "IgE",
        "IgG1",
        "IgG4",
        "mast cells",
        "IgE receptor",
        "allergic rhinoconjunctivitis",
        "grass pollen allergy"
      ]
    },
    "designModule": {
      "studyType": "INTERVENTIONAL",
      "phases": [
        "NA"
      ],
      "designInfo": {
        "allocation": "RANDOMIZED",
        "interventionModel": "PARALLEL",
        "primaryPurpose": "BASIC_SCIENCE",
        "maskingInfo": {
          "masking": "NONE"
        }
      },
      "enrollmentInfo": {
        "count": 30,
        "type": "ACTUAL"
      }
    },
    "armsInterventionsModule": {
      "armGroups": [
        {
          "label": "alutard phl prat. treatment group",
          "type": "ACTIVE_COMPARATOR",
          "description": "18 subjects receiving active treatment: basophil activity, plasma cells and immunoglobulins measured",
          "interventionNames": [
            "Biological: Alutard phleum pratense subcutaneous immunotherapy",
            "Drug: Alutard phl prat"
          ]
        },
        {
          "label": "control group",
          "type": "NO_INTERVENTION",
          "description": "control"
        },
        {
          "label": "alutard phl.prat., treatment group2",
          "type": "ACTIVE_COMPARATOR",
          "description": "basophil activity, basophil biology measured",
          "interventionNames": [
            "Biological: Alutard phleum pratense subcutaneous immunotherapy",
            "Drug: Alutard phl prat"
          ]
        }
      ],
      "interventions": [
        {
          "type": "BIOLOGICAL",
          "name": "Alutard phleum pratense subcutaneous immunotherapy",
          "description": "standard regimen of SCIT",
          "armGroupLabels": [
            "alutard phl prat. treatment group",
            "alutard phl.prat., treatment group2"
          ],
          "otherNames": [
            "alutard phleum pratense",
            "subcutaneous immunotherapy"
          ]
        },
        {
          "type": "DRUG",
          "name": "Alutard phl prat",
          "armGroupLabels": [
            "alutard phl prat. treatment group",
            "alutard phl.prat., treatment group2"
          ],
          "otherNames": [
            "Alutard 225, phleum pratense, ALK-abelló"
          ]
        }
      ]
    },
    "outcomesModule": {
      "primaryOutcomes": [
        {
          "measure": "a significant decrease in basophil activity during and after treatment",
          "timeFrame": "every 3 weeks for 3 months, then 3 monthly for 3 years"
        }
      ],
      "secondaryOutcomes": [
        {
          "measure": "reduction in high affinity IgE receptor density on basophils and mast cells",
          "description": "igE receptor density on basophils and mast cells from nasal mucosa",
          "timeFrame": "at inclusion and at the end of study"
        },
        {
          "measure": "clinical outcome: reduction in the reaction to allergen challenge tests (skin and nose), significant better outcome in quality of life questionnaires and symptom/medication scores",
          "description": "allergen challenging response",
          "timeFrame": "once yearly for 4 years"
        },
        {
          "measure": "a significant increase in the number of plasma cells during up dosing",
          "timeFrame": "5 times during the first 3 months of the study"
        },
        {
          "measure": "a significant shift in specific immunoglobulins from IgE at start to IgG1 and IgG4 after treatment. allergen epitope specific IgE and IgG4",
          "timeFrame": "every 3 months for 4 years"
        }
      ]
    },
    "eligibilityModule": {
      "eligibilityCriteria": "Inclusion Criteria:\n\n* rhinoconjunctivitis due to grass pollen allergy\n* positive skin prick test and nasal allergen challenge test to grass pollen extract\n\nExclusion Criteria:\n\n* severe comorbidity, severe asthma, pregnancy",
      "healthyVolunteers": false,
      "sex": "ALL",
      "minimumAge": "18 Years",
      "maximumAge": "40 Years",
      "stdAges": [
        "ADULT"
      ]
    },
    "contactsLocationsModule": {
      "overallOfficials": [
        {
          "name": "Ronald Dahl, Prof, dr.med",
          "affiliation": "Dept. of Respiratory Medicine, Århus University Hospital",
          "role": "STUDY_CHAIR"
        },
        {
          "name": "Hans Juergen Hoffmann, assoc prof",
          "affiliation": "Dept of Respiratory Medicine, Århus University Hospital",
          "role": "PRINCIPAL_INVESTIGATOR"
        },
        {
          "name": "Johannes M Schmid, MD",
          "affiliation": "Dept. of Respiratory Medicine, Aarhus University Hospital",
          "role": "PRINCIPAL_INVESTIGATOR"
        }
      ]
    }
  },
  "derivedSection": {
    "miscInfoModule": {
      "versionHolder": "2026-02-04"
    }
  },
  "hasResults": false
}